{
    "Student name is required": "Student name is required",
    "DateOfBirth is required": "DateOfBirth is required",
    "Gender is required": "Gender is required",
    "Address is required": "Address is required",
    "Date Of Joining is required": "Date Of Joining is required",
    "Department is required": "Department is required",
    "Grade is required": "Grade is required",
    "Parent name is required": "Parent name is required",
    "Parent relation is required": "Parent relation is required",
    "Parent job is required": "Parent job is required",
    "Parent phone is required": "Parent phone is required",
    "Student created successfully": "Student created successfully",
    "Expiration time must be greater than or equal 5 minutes.": "Expiration time must be greater than or equal 5 minutes.",
    "Password must be at least 6 characters": "Password must be at least 6 characters",
    "Invalid email format": "Invalid email format",
    "Email is required": "Email is required",
    "Email already exists": "Email already exists",
    "Invalid Credentials.": "Invalid Credentials.",
    "Login successfully": "Login successfully",
    "End time is required": "End time is required",
    "Start time is required": "Start time is required",
    "Date is required": "Date is required",
    "Lesson type is required": "Lesson type is required",
    "Title is required": "Title is required",
    "Subject is required": "Subject is required",
    "Teacher id is required": "Teacher id is required",
    "Lesson created successfully": "Lesson created successfully",
    "Lesson not found.": "Lesson not found.",
    "Classroom is not available in this time": "Classroom is not available in this time",
    "You can only join 5 minutes before the lesson starts.": "You can only join 5 minutes before the lesson starts.",
    "You cannot join , the lesson has ended.": "You cannot join , the lesson has ended.",
    "Token generated successfully": "Token generated successfully",
    "Lesson updated successfully": "Lesson updated successfully",
    "Lesson deleted successfully": "Lesson deleted successfully",
    "Validation.RecipientRequired": "Recipient email is required.",
    "Validation.InvalidEmail": "Invalid email format.",
    "Validation.SubjectRequired": "Subject is required.",
    "Validation.BodyRequired": "Email body is required.",
    "Email.Success": "Email sent successfully.",
    "Email.Failed": "Failed to send email: {0}",
    "Teacher created successfully": "Teacher created successfully",
    "Class Room Created successfully": "Class Room Created successfully",
    "There is no class with this id": "There is no class with this id",
    "Class Updated Successfully": "Class Updated Successfully",
    "Class Room Deleted Successfully": "Class Room Deleted Successfully",
    "Homework added Successfully": "Homework added Successfully",
    "HomeWork deleted successfully": "HomeWork deleted successfully",
    "HomeWork not found": "HomeWork not found",
    "Password reset email sent successfully": "Password reset email sent successfully",
    "This email isn't linked to any student or teacher account.": "This email isn't linked to any student or teacher account.",
    "EmailRequired": "Email is required.",
    "InvalidCodeFormat": "Invalid verification code format.",
    "NoResetCodeFound": "No reset code found for this email.",
    "IncorrectVerificationCode": "The provided verification code is incorrect.",
    "VerificationCodeExpired": "The verification code has expired. Please request a new one.",
    "VerificationSuccessful": "Verification successful.",
    "InternalServerError": "An error occurred while processing your request.",
    "PasswordMustBeAtLeast6Characters": "Password must be at least 6 characters.",
    "NoStudentFoundForEmail": "No student found for this email.",
    "PasswordResetSuccessful": "Password reset successful.",
    "Student is already assigned": "Student is already assigned",
    "Student not found": "Student not found",
    "Classroom not found": "Classroom not found",
    "Student assigned to classroom successfully": "Student assigned to classroom successfully",
    "Student is already not assigned": "Student is already not assigned",
    "Student delete from classroom successfully": "Student delete from classroom successfully",
    "Invalid email format.": "Invalid email format.",
    "Verification code is required": "Verification code is required",
    "Verification code must contain only numbers": "Verification code must contain only numbers",
    "Verification code must be exactly 6 digits": "Verification code must be exactly 6 digits",
    "Faild to join lesson" : "Faild to join lesson",
    "Lesson is already cancelled." : "Lesson is already cancelled.",
    "You are not authorized to cancel this lesson." : "You are not authorized to cancel this lesson.",
    "Lesson cancelled successfully." : "Lesson cancelled successfully.",

    "HomeWorkSubmittedSuccessfully": "HomeWork Submitted Successfully",
    "HomeWorkSubmissionClosed" : "HomeWork Submission Closed",
    "InvalidInput" : "InvalidInput"
}